setup.py
./__init__.py
./country.py
./currency.py
./lang.py
./party.py
./prestashop.py
./product.py
./sale.py
./tests/__init__.py
./tests/test_party.py
./tests/test_prestashop.py
./tests/test_product.py
./tests/test_sale.py
trytond_prestashop.egg-info/PKG-INFO
trytond_prestashop.egg-info/SOURCES.txt
trytond_prestashop.egg-info/dependency_links.txt
trytond_prestashop.egg-info/entry_points.txt
trytond_prestashop.egg-info/not-zip-safe
trytond_prestashop.egg-info/requires.txt
trytond_prestashop.egg-info/top_level.txt