Metadata-Version: 1.0
Name: trytond-prestashop
Version: 2.8.0.1dev
Summary: Prestashop Integration
Home-page: http://openlabs.co.in/
Author: Openlabs Technologies and Consulting P Ltd.
Author-email: UNKNOWN
License: GPL-3
Download-URL: https://github.com/openlabs/trytond-prestashop
Platform: UNKNOWN
Classifier: Development Status :: 4 - Beta
Classifier: Environment :: Plugins
Classifier: Framework :: Tryton
Classifier: Intended Audience :: Developers
Classifier: Intended Audience :: Financial and Insurance Industry
Classifier: Intended Audience :: Legal Industry
Classifier: Intended Audience :: Manufacturing
Classifier: License :: OSI Approved :: GNU General Public License (GPL)
Classifier: Natural Language :: English
Classifier: Operating System :: OS Independent
Classifier: Programming Language :: Python :: 2.6
Classifier: Programming Language :: Python :: 2.7
Classifier: Topic :: Office/Business
